fit_plot.py
fit_plot-0.1.12.dist-info/licenses/LICENSE
fit_plot-0.1.12.dist-info/METADATA
fit_plot-0.1.12.dist-info/WHEEL
fit_plot-0.1.12.dist-info/top_level.txt
fit_plot-0.1.12.dist-info/RECORD
