Metadata-Version: 2.4
Name: fit_plot
Version: 0.1.12
Summary: Tool for fitting lines to data
Author: Carl Michal, Paul Ripoche
Maintainer-email: Carl Michal <michal@physics.ubc.ca>
Classifier: Development Status :: 3 - Alpha
Classifier: Intended Audience :: Science/Research
Classifier: Intended Audience :: Education
Classifier: License :: OSI Approved :: GNU General Public License v3 (GPLv3)
Classifier: Programming Language :: Python :: 3
Requires-Python: >=3.7
License-File: LICENSE
Requires-Dist: ipympl>=0.9.4
Dynamic: license-file
